fritzsms/fritzbox.py
pyfritzsms-1.1.3.dist-info/METADATA
pyfritzsms-1.1.3.dist-info/WHEEL
pyfritzsms-1.1.3.dist-info/licenses/LICENSE
pyfritzsms-1.1.3.dist-info/RECORD
