Metadata-Version: 2.4
Name: pyfritzsms
Version: 1.1.3
Summary: Python library to send SMS via AVM FRITZ!Box
Author-email: Marc Hoersken <info@marc-hoersken.de>
License-Expression: Apache-2.0
License-File: LICENSE
Keywords: fritzbox,sms
Requires-Python: >=3.9
Requires-Dist: aiohttp>=3.11.18
Requires-Dist: pyotp>=2.9.0
